.VERSION
AUTHORS.rst
CONTRIBUTING.rst
HISTORY.rst
LICENSE
MANIFEST.in
Pipfile
Pipfile.lock
README.rst
USAGE.rst
dev-requirements.txt
requirements.txt
setup.cfg
setup.py
docs/Makefile
docs/authors.rst
docs/conf.py
docs/contributing.rst
docs/history.rst
docs/index.rst
docs/installation.rst
docs/readme.rst
docs/usage.rst
myawesomecli2cli/.VERSION
myawesomecli2cli/AUTHORS.rst
myawesomecli2cli/CONTRIBUTING.rst
myawesomecli2cli/HISTORY.rst
myawesomecli2cli/LICENSE
myawesomecli2cli/Pipfile
myawesomecli2cli/Pipfile.lock
myawesomecli2cli/README.rst
myawesomecli2cli/USAGE.rst
myawesomecli2cli/__init__.py
myawesomecli2cli/_version.py
myawesomecli2cli/dev-requirements.txt
myawesomecli2cli/myawesomecli2cli.py
myawesomecli2cli/myawesomecli2cliexceptions.py
myawesomecli2cli/requirements.txt
myawesomecli2cli.egg-info/PKG-INFO
myawesomecli2cli.egg-info/SOURCES.txt
myawesomecli2cli.egg-info/dependency_links.txt
myawesomecli2cli.egg-info/entry_points.txt
myawesomecli2cli.egg-info/not-zip-safe
myawesomecli2cli.egg-info/requires.txt
myawesomecli2cli.egg-info/top_level.txt
myawesomecli2cli/conf/logging.json-example