Metadata-Version: 2.1
Name: myawesomecli2cli
Version: 1.0.1
Summary: A template to create python libraries
Home-page: https://github.com/RynoM/MyAwesomeCLI2
Author: Ryno Marree
Author-email: ryno.marree@hotmail.com
License: MIT
Keywords: myawesomecli2cli
Platform: UNKNOWN
Classifier: Development Status :: 2 - Pre-Alpha
Classifier: Intended Audience :: Developers
Classifier: License :: OSI Approved :: MIT License
Classifier: Natural Language :: English
Classifier: Programming Language :: Python :: 3.7
License-File: LICENSE
License-File: AUTHORS.rst
